dragonx_optimizer/__init__.py
dragonx_optimizer/common_models.py
dragonx_optimizer/generator.py
dragonx_optimizer/results.py
dragonx_optimizer/src_main.py
dragonx_optimizer/algorithms/__init__.py
dragonx_optimizer/algorithms/algo_optim.py
dragonx_optimizer/algorithms/transformations.py
dragonx_optimizer/ir/__init__.py
dragonx_optimizer/ir/ddfg_main.py
dragonx_optimizer/ir/flatten.py
dragonx_optimizer/ir/graph.py
dragonx_optimizer/ir/handlers.py
dragonx_optimizer/ir/node.py
dragonx_optimizer/ir/trace.py
dragonx_optimizer/ir/variable.py
dragonx_optimizer/ir/cfg/__init__.py
dragonx_optimizer/ir/cfg/main.py
dragonx_optimizer/ir/cfg/setup.py
dragonx_optimizer/ir/cfg/examples/__init__.py
dragonx_optimizer/ir/cfg/examples/build_cfg.py
dragonx_optimizer/ir/cfg/staticfg/__init__.py
dragonx_optimizer/ir/cfg/staticfg/builder.py
dragonx_optimizer/ir/cfg/staticfg/model.py
dragonx_optimizer/ir/cfg/tests/__init__.py
dragonx_optimizer/ir/cfg/tests/test_model.py
dragonx_optimizer/mapper/__init__.py
dragonx_optimizer/mapper/mapper.py
dragonx_optimizer/mapper/mappings.py
dragonx_optimizer/models/Unet.py
dragonx_optimizer/models/__init__.py
dragonx_optimizer/models/a3c_model.py
dragonx_optimizer/models/base_model_r34.py
dragonx_optimizer/models/dart_model.py
dragonx_optimizer/models/gan_model.py
dragonx_optimizer/models/gnn_model.py
dragonx_optimizer/models/hpcg.py
dragonx_optimizer/models/rnn.py
dragonx_optimizer/models/rnnt.py
dragonx_optimizer/models/ssd_rs34.py
dragonx_optimizer/synthesis/__init__.py
dragonx_optimizer/synthesis/ai_utils.py
dragonx_optimizer/synthesis/dataflow_solver.py
dragonx_optimizer/synthesis/hls.py
dragonx_optimizer/synthesis/loop_blocking.py
dragonx_optimizer/synthesis/map_eyeriss.py
dragonx_optimizer/synthesis/parallel_enum.py
dragonx_optimizer/synthesis/partition.py
dragonx_optimizer/synthesis/schedule.py
dragonx_optimizer/tables/__init__.py
dragonx_optimizer/utils/__init__.py
dragonx_optimizer/utils/dot.py
dragonx_optimizer/utils/logger.py
dragonx_optimizer-0.1.1.dist-info/LICENSE
dragonx_optimizer-0.1.1.dist-info/METADATA
dragonx_optimizer-0.1.1.dist-info/WHEEL
dragonx_optimizer-0.1.1.dist-info/top_level.txt
dragonx_optimizer-0.1.1.dist-info/RECORD
